{
  "id": "hsc_bangla_story_oporichita_5",
  "name": "অপরিচিতা ৫",
  "type": "story",
  "parts": [
    {
      "text": "বাড়ি ফিরিবার সময় ব্যান্ড, রসনচৌকি ও কন্সর্ট একসঙ্গে আর বাজিল না। সমস্ত আনন্দ যেন হঠাৎ স্তব্ধ হইয়া গেল। অভ্রের ঝাড়গুলিও অদৃশ্য হইয়া গেল, যেন সমস্ত উৎসবের আলো নিভিয়া গিয়াছে।",
      "questions": [
        {
          "id": "q1",
          "type": "mcq",
          "question": "বাড়ি ফেরার সময় পরিবেশ কেমন ছিল?",
          "options": [
            "আনন্দময়",
            "উৎসবমুখর",
            "নিস্তব্ধ ও নিরানন্দ",
            "কোলাহলপূর্ণ"
          ],
          "answer": "নিস্তব্ধ ও নিরানন্দ",
          "explanation": "বিবাহ ভেঙে যাওয়ায় সব আনন্দ থেমে যায়।"
        }
      ]
    },
    {
      "text": "বাড়ির সকলে রাগে ফেটে পড়ল। কন্যার পিতার এত গুমর দেখে সবাই ক্ষুব্ধ হলো। তারা বলতে লাগল, এখন দেখা যাবে তিনি কীভাবে মেয়ের বিয়ে দেন।",
      "questions": [
        {
          "id": "q2",
          "type": "gapfill",
          "question": "সকলেই কন্যার ___ উপর রাগ করেছিল।",
          "wordBank": ["পিতা", "মাতা", "ভাই", "বন্ধু"],
          "answer": "পিতা",
          "explanation": "সবাই কন্যার পিতার উপর রাগান্বিত ছিল।"
        }
      ]
    },
    {
      "text": "লেখক ভাবলেন, এত বড়ো অপমান আর কারও জীবনে ঘটে নাই। তিনি নিজেকে একমাত্র ব্যক্তি মনে করলেন যাকে বিবাহের আসর থেকে ফিরিয়ে দেওয়া হয়েছে।",
      "questions": [
        {
          "id": "q3",
          "type": "mcq",
          "question": "লেখক নিজের সম্পর্কে কী ভাবলেন?",
          "options": [
            "তিনি সফল",
            "তিনি অপমানিত",
            "তিনি গর্বিত",
            "তিনি সুখী"
          ],
          "answer": "তিনি অপমানিত",
          "explanation": "তিনি এটিকে জীবনের বড় অপমান হিসেবে দেখেছেন।"
        }
      ]
    },
    {
      "text": "বরযাত্রীরা রাগে কপাল চাপড়াতে লাগল। তারা বলল, বিয়ে না হলেও তাদের খাওয়ানো হয়েছে—এটি তাদের কাছে অপমানজনক।",
      "questions": [
        {
          "id": "q4",
          "type": "mcq",
          "question": "বরযাত্রীদের রাগের একটি কারণ কী ছিল?",
          "options": [
            "খাবার খারাপ ছিল",
            "তাদের খাওয়ানো হয়নি",
            "বিয়ে না হয়েও খাওয়ানো হয়েছে",
            "তারা দেরি করেছিল"
          ],
          "answer": "বিয়ে না হয়েও খাওয়ানো হয়েছে",
          "explanation": "এটি তাদের অপমান মনে হয়েছিল।"
        }
      ]
    },
    {
      "text": "মামা চুক্তিভঙ্গ ও মানহানির জন্য মামলা করতে চাইলেন। কিন্তু হিতৈষীরা তাঁকে বোঝালেন, এতে পরিস্থিতি আরও খারাপ হবে।",
      "questions": [
        {
          "id": "q5",
          "type": "match",
          "pairs": [
            { "left": "মামা", "right": "মামলা করতে চান" },
            { "left": "হিতৈষী", "right": "বাধা দেন" },
            { "left": "ঘটনা", "right": "মানহানি" }
          ]
        }
      ]
    },
    {
      "text": "লেখক বাইরে রাগ দেখালেও ভিতরে অন্য অনুভূতি কাজ করছিল। সেই অচেনা মেয়েটির প্রতি তাঁর মনে আকর্ষণ তৈরি হয়েছিল।",
      "questions": [
        {
          "id": "q6",
          "type": "mcq",
          "question": "লেখকের মনে কী অনুভূতি তৈরি হয়েছিল?",
          "options": [
            "ঘৃণা",
            "ভয়",
            "আকর্ষণ",
            "উদাসীনতা"
          ],
          "answer": "আকর্ষণ",
          "explanation": "তিনি মেয়েটির প্রতি আকৃষ্ট হয়েছিলেন।"
        }
      ]
    },
    {
      "text": "তিনি কল্পনায় মেয়েটির রূপ আঁকতে থাকেন—কপালে চন্দন, গায়ে লাল শাড়ি, মুখে লজ্জার আভা। কিন্তু বাস্তবে কখনো তাকে দেখেননি।",
      "questions": [
        {
          "id": "q7",
          "type": "gapfill",
          "question": "লেখক মেয়েটিকে বাস্তবে কখনো ___ দেখেননি।",
          "wordBank": ["চোখে", "স্বপ্নে", "মনে", "ছবিতে"],
          "answer": "চোখে",
          "explanation": "তিনি কেবল কল্পনায় দেখেছিলেন।"
        }
      ]
    },
    {
      "text": "বিনুদাদার সংক্ষিপ্ত বর্ণনা থেকেই লেখকের মনে মেয়েটির একটি আকর্ষণীয় ছবি গড়ে ওঠে। সেই কল্পনা তাঁকে বারবার টানতে থাকে।",
      "questions": [
        {
          "id": "q8",
          "type": "mcq",
          "question": "মেয়েটির সম্পর্কে ধারণা লেখক কার কাছ থেকে পান?",
          "options": [
            "হরিশ",
            "মামা",
            "বিনুদাদা",
            "শম্ভুনাথবাবু"
          ],
          "answer": "বিনুদাদা",
          "explanation": "বিনুদাদার বর্ণনা থেকেই ধারণা পেয়েছিলেন।"
        }
      ]
    },
    {
      "text": "লেখক কল্পনা করেন, মেয়েটি হয়তো তাঁর ছবি লুকিয়ে রাখে এবং একা একা দেখে। এই ভাবনাগুলো তাঁর মনে গভীর প্রভাব ফেলে।",
      "questions": [
        {
          "id": "q9",
          "type": "mcq",
          "question": "লেখক কী কল্পনা করেন?",
          "options": [
            "মেয়েটি তাঁকে ভুলে গেছে",
            "মেয়েটি তাঁর ছবি দেখে",
            "মেয়েটি রাগ করে আছে",
            "মেয়েটি অন্যত্র বিয়ে করেছে"
          ],
          "answer": "মেয়েটি তাঁর ছবি দেখে",
          "explanation": "তিনি কল্পনা করেন মেয়েটি তাঁর ছবি দেখে।"
        }
      ]
    },
    {
      "text": "দিন যেতে থাকে। একটি বছর কেটে যায়। অপমানের কারণে মামা আর বিয়ের কথা তুলতে পারেন না, আর মা অপেক্ষা করতে থাকেন।",
      "questions": [
        {
          "id": "q10",
          "type": "gapfill",
          "question": "___ বছর কেটে যায়।",
          "wordBank": ["এক", "দুই", "তিন", "চার"],
          "answer": "এক",
          "explanation": "গল্পে বলা হয়েছে এক বছর কেটে গেছে।"
        }
      ]
    }
  ]
}
